mliseuvce/__init__.py
mliseuvce/functions.py
mliseuvce-0.1.0.dist-info/METADATA
mliseuvce-0.1.0.dist-info/WHEEL
mliseuvce-0.1.0.dist-info/top_level.txt
mliseuvce-0.1.0.dist-info/RECORD
