Metadata-Version: 2.1
Name: mliseuvce
Version: 0.1.0
Summary: A collection of educational ML and ANN functions
Home-page: https://github.com/Ganesh57803/mluvmodel
Author: no author
Author-email: my@gmail.com
Classifier: Programming Language :: Python :: 3
Classifier: License :: OSI Approved :: MIT License
Classifier: Operating System :: OS Independent
Requires-Python: >=3.6
